devskin_agent/__init__.py
devskin_agent/agent.py
devskin_agent/api_client.py
devskin_agent/span.py
devskin_agent/types.py
devskin_agent/instrumentation/__init__.py
devskin_agent/instrumentation/django_middleware.py
devskin_agent/instrumentation/fastapi_middleware.py
devskin_agent/instrumentation/flask_middleware.py
devskin_agent/utils/__init__.py
devskin_agent/utils/context.py
devskin_agent/utils/id_generator.py
devskin_agent-1.0.0.dist-info/licenses/LICENSE
devskin_agent-1.0.0.dist-info/METADATA
devskin_agent-1.0.0.dist-info/WHEEL
devskin_agent-1.0.0.dist-info/top_level.txt
devskin_agent-1.0.0.dist-info/RECORD
