Metadata-Version: 2.4
Name: devskin-agent
Version: 1.0.0
Summary: DevSkin Monitor Agent - Python Instrumentation SDK
Home-page: https://github.com/devskin/devskin-monitor
Author: DevSkin Team
Author-email: DevSkin Team <team@devskin.monitor>
Project-URL: Homepage, https://devskin.com
Project-URL: Documentation, https://docs.devskin.com
Project-URL: Repository, https://github.com/devskin1/devskin-monitoring-python-agent
Keywords: monitoring,apm,agent,instrumentation,observability,tracing,logging,metrics
Classifier: Development Status :: 4 - Beta
Classifier: Intended Audience :: Developers
Classifier: Topic :: System :: Monitoring
Classifier: License :: OSI Approved :: MIT License
Classifier: Programming Language :: Python :: 3
Classifier: Programming Language :: Python :: 3.8
Classifier: Programming Language :: Python :: 3.9
Classifier: Programming Language :: Python :: 3.10
Classifier: Programming Language :: Python :: 3.11
Requires-Python: >=3.8
License-File: LICENSE
Requires-Dist: requests>=2.31.0
Requires-Dist: opentelemetry-api>=1.21.0
Requires-Dist: opentelemetry-sdk>=1.21.0
Provides-Extra: dev
Requires-Dist: pytest>=7.4.0; extra == "dev"
Requires-Dist: pytest-cov>=4.1.0; extra == "dev"
Requires-Dist: black>=23.12.0; extra == "dev"
Requires-Dist: mypy>=1.7.0; extra == "dev"
Dynamic: author
Dynamic: home-page
Dynamic: license-file
Dynamic: requires-python
